odoo/addons/purchase_manual_delivery/README.rst
odoo/addons/purchase_manual_delivery/__init__.py
odoo/addons/purchase_manual_delivery/__manifest__.py
odoo/addons/purchase_manual_delivery/i18n/es.po
odoo/addons/purchase_manual_delivery/i18n/it.po
odoo/addons/purchase_manual_delivery/i18n/pt_BR.po
odoo/addons/purchase_manual_delivery/i18n/purchase_manual_delivery.pot
odoo/addons/purchase_manual_delivery/i18n/sl.po
odoo/addons/purchase_manual_delivery/migrations/17.0.1.0.0/pre-migration.py
odoo/addons/purchase_manual_delivery/models/__init__.py
odoo/addons/purchase_manual_delivery/models/product_product.py
odoo/addons/purchase_manual_delivery/models/purchase_order.py
odoo/addons/purchase_manual_delivery/models/purchase_order_line.py
odoo/addons/purchase_manual_delivery/models/res_company.py
odoo/addons/purchase_manual_delivery/models/res_config.py
odoo/addons/purchase_manual_delivery/readme/CONFIGURE.md
odoo/addons/purchase_manual_delivery/readme/CONTRIBUTORS.md
odoo/addons/purchase_manual_delivery/readme/DESCRIPTION.md
odoo/addons/purchase_manual_delivery/readme/USAGE.md
odoo/addons/purchase_manual_delivery/report/__init__.py
odoo/addons/purchase_manual_delivery/report/stock_forecasted.py
odoo/addons/purchase_manual_delivery/security/ir.model.access.csv
odoo/addons/purchase_manual_delivery/static/description/create_incoming_shipment_button.png
odoo/addons/purchase_manual_delivery/static/description/create_incoming_shipment_wizard.png
odoo/addons/purchase_manual_delivery/static/description/icon.png
odoo/addons/purchase_manual_delivery/static/description/index.html
odoo/addons/purchase_manual_delivery/static/src/purchase_manual_delivery_forecasted/forecasted_details.xml
odoo/addons/purchase_manual_delivery/tests/__init__.py
odoo/addons/purchase_manual_delivery/tests/test_purchase_manual_delivery.py
odoo/addons/purchase_manual_delivery/tests/test_report_forecast.py
odoo/addons/purchase_manual_delivery/views/purchase_order_line_views.xml
odoo_addon_purchase_manual_delivery-18.0.1.0.0.6.dist-info/METADATA
odoo_addon_purchase_manual_delivery-18.0.1.0.0.6.dist-info/WHEEL
odoo_addon_purchase_manual_delivery-18.0.1.0.0.6.dist-info/top_level.txt
odoo_addon_purchase_manual_delivery-18.0.1.0.0.6.dist-info/RECORD
