Metadata-Version: 2.1
Name: odoo-addon-purchase_manual_delivery
Version: 18.0.1.0.0.6
Requires-Python: >=3.10
Requires-Dist: odoo-addon-purchase_order_line_menu==18.0.*
Requires-Dist: odoo==18.0.*
Summary: Prevents pickings to be auto generated upon Purchase Order confirmation and adds the ability to manually generate them as the supplier confirms the different purchase order lines.
Home-page: https://github.com/OCA/purchase-workflow
License: AGPL-3
Author: ForgeFlow S.L.,Odoo Community Association (OCA)
Author-email: support@odoo-community.org
Classifier: Programming Language :: Python
Classifier: Framework :: Odoo
Classifier: Framework :: Odoo :: 18.0
Classifier: License :: OSI Approved :: GNU Affero General Public License v3
